{
    "TOTAL": {
        "lines": 7896,
        "files": 188
    },
    "PLAIN": {
        "files": 1,
        "lines": 13
    },
    ".md": {
        "files": 3,
        "lines": 392
    },
    ".json": {
        "files": 9,
        "lines": 192
    },
    ".ts": {
        "files": 72,
        "lines": 2447
    },
    ".js": {
        "files": 38,
        "lines": 1629
    },
    ".map": {
        "files": 35,
        "lines": 35
    },
    ".info": {
        "files": 1,
        "lines": 15
    },
    ".css": {
        "files": 2,
        "lines": 226
    },
    ".html": {
        "files": 15,
        "lines": 2026
    },
    ".MD": {
        "files": 2,
        "lines": 2
    },
    ".yaml": {
        "files": 2,
        "lines": 780
    },
    ".gql": {
        "files": 8,
        "lines": 139
    }
}
{"TOTAL":{"lines":8735,"files":215},"PLAIN":{"files":1,"lines":13},".md":{"files":3,"lines":409},".json":{"files":9,"lines":246},".ts":{"files":71,"lines":2502},".map":{"files":49,"lines":49},".js":{"files":52,"lines":2303},".info":{"files":1,"lines":22},".MD":{"files":2,"lines":2},".css":{"files":2,"lines":226},".html":{"files":15,"lines":2044},".yaml":{"files":2,"lines":780},".gql":{"files":8,"lines":139}}
