{"TOTAL":{"lines":20372,"files":190},".md":{"files":5,"lines":801},"PLAIN":{"files":1,"lines":13},".json":{"files":14,"lines":213},".ts":{"files":114,"lines":5515},".js":{"files":4,"lines":294},".map":{"files":1,"lines":1},".rdb":{"files":1,"lines":6},".css":{"files":2,"lines":226},".html":{"files":15,"lines":2044},".info":{"files":1,"lines":22},".MD":{"files":2,"lines":2},".bson":{"files":4,"lines":834},".kdenlive":{"files":1,"lines":409},".yaml":{"files":12,"lines":9710},".gql":{"files":13,"lines":282}}
